pycrypt/PasswdGenerator.py
pycrypt/__init__.py
pycrypt/credstore.py
pycrypt/encryption.py
pycrypt/pkcs7.py
pycrypt_samn-1.3.2.dist-info/METADATA
pycrypt_samn-1.3.2.dist-info/WHEEL
pycrypt_samn-1.3.2.dist-info/top_level.txt
pycrypt_samn-1.3.2.dist-info/RECORD
