Metadata-Version: 2.1
Name: pycrypt-samn
Version: 1.3.2
Summary: Customized Encryption module
Home-page: https://github.com/ToxicSamN/pycrypt
Author: Sammy Shuck github.com/ToxicSamN
License: Apache
Keywords: pycrypt,pycrypt-samn
Platform: UNKNOWN
Requires-Dist: certifi (>=2020.6.20)
Requires-Dist: chardet (>=3.0.4)
Requires-Dist: idna (>=2.10)
Requires-Dist: pycrypt-samn (>=1.2.7)
Requires-Dist: pycryptodome (>=3.9.8)
Requires-Dist: requests (>=2.24.0)
Requires-Dist: six (>=1.15.0)
Requires-Dist: urllib3 (>=1.25.10)
